selenium_chatbot_test/__init__.py
selenium_chatbot_test/assertions.py
selenium_chatbot_test/metrics.py
selenium_chatbot_test/py.typed
selenium_chatbot_test/waiters.py
selenium_chatbot_test-0.2.0.dist-info/METADATA
selenium_chatbot_test-0.2.0.dist-info/WHEEL
selenium_chatbot_test-0.2.0.dist-info/top_level.txt
selenium_chatbot_test-0.2.0.dist-info/RECORD
