Metadata-Version: 2.4
Name: selenium-chatbot-test
Version: 0.2.0
Summary: A library for testing Generative AI interfaces with Selenium WebDriver
Author-email: Dhiraj Das <dhirajdas.666@gmail.com>
License: MIT
Project-URL: Homepage, https://www.dhirajdas.dev
Project-URL: Repository, https://github.com/godhiraj-code/selenium-chatbot-test.git
Project-URL: Issues, https://github.com/godhiraj-code/selenium-chatbot-test/issues
Keywords: selenium,testing,chatbot,ai,generative-ai,llm,streaming,webdriver,automation
Classifier: Development Status :: 4 - Beta
Classifier: Intended Audience :: Developers
Classifier: License :: OSI Approved :: MIT License
Classifier: Operating System :: OS Independent
Classifier: Programming Language :: Python :: 3
Classifier: Programming Language :: Python :: 3.9
Classifier: Programming Language :: Python :: 3.10
Classifier: Programming Language :: Python :: 3.11
Classifier: Programming Language :: Python :: 3.12
Classifier: Topic :: Software Development :: Testing
Classifier: Topic :: Software Development :: Quality Assurance
Classifier: Framework :: Pytest
Requires-Python: >=3.9
Requires-Dist: selenium>=4.0.0
Requires-Dist: sentence-transformers>=2.2.0
Requires-Dist: numpy>=1.21.0
Provides-Extra: dev
Requires-Dist: pytest>=7.0.0; extra == "dev"
Requires-Dist: pytest-cov>=4.0.0; extra == "dev"
Requires-Dist: black>=23.0.0; extra == "dev"
Requires-Dist: isort>=5.12.0; extra == "dev"
Requires-Dist: mypy>=1.0.0; extra == "dev"
